[{"team":"New Jersey","2022-09-29":"New York","2022-09-30":"New York","2022-10-01":"","2022-10-02":""},{"team":"New York","2022-09-29":"","2022-09-30":"","2022-10-01":"","2022-10-02":"Philadelphia"},{"team":"New York","2022-09-29":"New Jersey","2022-09-30":"New Jersey","2022-10-01":"","2022-10-02":""},{"team":"Philadelphia","2022-09-29":"","2022-09-30":"","2022-10-01":"Boston","2022-10-02":"New York"},{"team":"Pittsburgh","2022-09-29":"","2022-09-30":"","2022-10-01":"Buffalo","2022-10-02":""},{"team":"Boston","2022-09-29":"","2022-09-30":"","2022-10-01":"Philadelphia","2022-10-02":""},{"team":"Buffalo","2022-09-29":"","2022-09-30":"","2022-10-01":"Pittsburgh","2022-10-02":""},{"team":"Montréal","2022-09-29":"Winnipeg","2022-09-30":"","2022-10-01":"Ottawa","2022-10-02":""},{"team":"Ottawa","2022-09-29":"","2022-09-30":"Toronto","2022-10-01":"Montréal","2022-10-02":""},{"team":"Toronto","2022-09-29":"","2022-09-30":"Ottawa","2022-10-01":"","2022-10-02":""},{"team":"Carolina","2022-09-29":"Florida","2022-09-30":"","2022-10-01":"Florida","2022-10-02":""},{"team":"Florida","2022-09-29":"Carolina","2022-09-30":"","2022-10-01":"Carolina","2022-10-02":""},{"team":"Tampa Bay","2022-09-29":"Nashville","2022-09-30":"Nashville","2022-10-01":"","2022-10-02":""},{"team":"Washington","2022-09-29":"","2022-09-30":"Detroit","2022-10-01":"Columbus","2022-10-02":""},{"team":"Chicago","2022-09-29":"","2022-09-30":"","2022-10-01":"Detroit","2022-10-02":"Minnesota"},{"team":"Detroit","2022-09-29":"","2022-09-30":"Washington","2022-10-01":"Chicago","2022-10-02":""},{"team":"Nashville","2022-09-29":"Tampa Bay","2022-09-30":"Tampa Bay","2022-10-01":"","2022-10-02":""},{"team":"St. Louis","2022-09-29":"Columbus","2022-09-30":"","2022-10-01":"Dallas","2022-10-02":""},{"team":"Calgary","2022-09-29":"","2022-09-30":"Edmonton","2022-10-01":"","2022-10-02":""},{"team":"Colorado","2022-09-29":"","2022-09-30":"","2022-10-01":"","2022-10-02":""},{"team":"Edmonton","2022-09-29":"","2022-09-30":"Calgary","2022-10-01":"Winnipeg","2022-10-02":""},{"team":"Vancouver","2022-09-29":"Seattle","2022-09-30":"","2022-10-01":"Seattle","2022-10-02":""},{"team":"Anaheim","2022-09-29":"","2022-09-30":"San Jose","2022-10-01":"","2022-10-02":"Los Angeles"},{"team":"Dallas","2022-09-29":"Minnesota","2022-09-30":"","2022-10-01":"St. Louis","2022-10-02":""},{"team":"Los Angeles","2022-09-29":"","2022-09-30":"","2022-10-01":"","2022-10-02":"Anaheim"},{"team":"San Jose","2022-09-29":"","2022-09-30":"Vegas","2022-10-01":"","2022-10-02":""},{"team":"Columbus","2022-09-29":"St. Louis","2022-09-30":"","2022-10-01":"Washington","2022-10-02":""},{"team":"Minnesota","2022-09-29":"Dallas","2022-09-30":"","2022-10-01":"","2022-10-02":"Chicago"},{"team":"Winnipeg","2022-09-29":"Montréal","2022-09-30":"","2022-10-01":"Edmonton","2022-10-02":""},{"team":"Arizona","2022-09-29":"","2022-09-30":"","2022-10-01":"","2022-10-02":""},{"team":"Vegas","2022-09-29":"","2022-09-30":"San Jose","2022-10-01":"","2022-10-02":""},{"team":"Seattle","2022-09-29":"Vancouver","2022-09-30":"","2022-10-01":"Vancouver","2022-10-02":""}]